mdp/__init__.py
mdp/__main__.py
mdp/src/__init__.py
mdp/src/uc_mdp/__init__.py
mdp/src/uc_mdp/mdp.py
mdp/src/uc_mdp/problem.py
mdp/src/uc_mdp/uc_mdp_main.py
mdp/util/__init__.py
mdp/util/data_input_loader.py
markovdecisionprocess-0.0.1.dist-info/LICENSE
markovdecisionprocess-0.0.1.dist-info/METADATA
markovdecisionprocess-0.0.1.dist-info/WHEEL
markovdecisionprocess-0.0.1.dist-info/top_level.txt
markovdecisionprocess-0.0.1.dist-info/RECORD
