Metadata-Version: 2.1
Name: markovdecisionprocess
Version: 0.0.1
Summary: Markov Decision Process
Home-page: https://github.com/ga74kud/mdp
Author: Michael Hartmann
Author-email: michael.hartmann@v2c2.at
License: GNU GENERAL PUBLIC LICENSE
Platform: UNKNOWN
Requires-Dist: scipy
Requires-Dist: numpy
Requires-Dist: matplotlib
Requires-Dist: argparse
Requires-Dist: logging
Requires-Dist: igraph
Requires-Dist: pycairo
Requires-Dist: plotly
Requires-Dist: pandas
